leaninit/__init__.py
leaninit/cli.py
leaninit/elf.py
leaninit/lz4l.py
leaninit-0.0.9.dist-info/METADATA
leaninit-0.0.9.dist-info/WHEEL
leaninit-0.0.9.dist-info/licenses/LICENSE
leaninit-0.0.9.dist-info/RECORD
