Metadata-Version: 2.4
Name: leaninit
Version: 0.0.9
Summary: Compression of initialized data and/or code for embedded systems.
Project-URL: Homepage, https://github.com/sebastien-riou/lean-init
Project-URL: Bug Tracker, https://github.com/sebastien-riou/lean-init/issues
Author: Sebastien Riou
License-File: LICENSE
Classifier: Development Status :: 4 - Beta
Classifier: License :: OSI Approved :: Apache Software License
Classifier: Operating System :: OS Independent
Classifier: Programming Language :: Python :: 3.10
Classifier: Programming Language :: Python :: 3.11
Classifier: Programming Language :: Python :: 3.12
Classifier: Programming Language :: Python :: Implementation :: CPython
Classifier: Programming Language :: Python :: Implementation :: PyPy
Requires-Python: >=3.10
Requires-Dist: humanfriendly
Provides-Extra: build
Requires-Dist: build; extra == 'build'
Provides-Extra: doc
Requires-Dist: sphinx; extra == 'doc'
